spampost/__init__.py
spampost-1.0.5.dist-info/METADATA
spampost-1.0.5.dist-info/WHEEL
spampost-1.0.5.dist-info/entry_points.txt
spampost-1.0.5.dist-info/top_level.txt
spampost-1.0.5.dist-info/RECORD
