Metadata-Version: 2.1
Name: spampost
Version: 1.0.5
Summary: Check blog's spam post
Home-page: https://github.com/narupo/spampost
Author: narupo
Author-email: narupo.glab@gmail.com
License: MIT
Platform: UNKNOWN
Classifier: License :: OSI Approved :: MIT License
Classifier: Programming Language :: Python :: 3
Classifier: Programming Language :: Python :: 3.7
Requires-Dist: BeautifulSoup4
Requires-Dist: soupsieve
Requires-Dist: janome
